{
  "_generated": "Generated by SweetTooth, do not edit", 
  "description": "Extended fork of original Gnome Workspace Indicator, which shows all workspaces.", 
  "extension-id": "workspace-indicator-extended", 
  "gettext-domain": "gnome-shell-extensions", 
  "name": "Workspace Indicator Extended", 
  "original-authors": [
    "mail@sebastian-bus.ch",
    "erick.red@gmail.com"
  ], 
  "settings-schema": "org.gnome.shell.extensions.sbusch-workspace-indicator-extended", 
  "shell-version": [
    "3.20"
  ], 
  "url": "https://github.com/sbusch/gnome-shell-extensions/",
  "uuid": "workspace-indicator-extended@github.com--sbusch--gnome-shell-extensions", 
  "version": 1
}